dj_lite/__init__.py
dj_lite/configurator.py
dj_lite/enums.py
dj_lite-1.3.0.dist-info/WHEEL
dj_lite-1.3.0.dist-info/METADATA
dj_lite-1.3.0.dist-info/RECORD
