Metadata-Version: 2.4
Name: dj-lite
Version: 1.3.0
Summary: Configure SQLite for production use with Django.
License-Expression: MIT
Classifier: Development Status :: 4 - Beta
Classifier: Framework :: Django
Classifier: Framework :: Django :: 5.1
Classifier: Framework :: Django :: 5.2
Classifier: Framework :: Django :: 6
Classifier: Framework :: Django :: 6.0
Classifier: Programming Language :: Python
Classifier: Programming Language :: Python :: 3.10
Classifier: Programming Language :: Python :: 3.11
Classifier: Programming Language :: Python :: 3.12
Classifier: Programming Language :: Python :: 3.13
Classifier: Programming Language :: Python :: 3.14
Classifier: Programming Language :: Python :: 3.15
Classifier: Programming Language :: Python :: 3.9
Classifier: Typing :: Typed
Requires-Dist: typeguard>=2
Requires-Python: >=3.9.7
Project-URL: homepage, https://github.com/adamghill/dj-lite/
Project-URL: repository, https://github.com/adamghill/dj-lite.git
